inspirobot/__init__.py
inspirobot/error.py
inspirobot/flow.py
inspirobot/generate.py
insprio-0.0.1.dist-info/LICENSE
insprio-0.0.1.dist-info/METADATA
insprio-0.0.1.dist-info/WHEEL
insprio-0.0.1.dist-info/top_level.txt
insprio-0.0.1.dist-info/RECORD
