Metadata-Version: 2.1
Name: insprio
Version: 0.0.1
Summary: Python3 API wrapper for InspiroBot
Home-page: https://github.com/samhdev/insprio
Author: SamHDev
Author-email: sam02h.huddart@gmail.com
License: UNKNOWN
Platform: UNKNOWN
Classifier: Programming Language :: Python :: 3
Classifier: License :: OSI Approved :: MIT License
Classifier: Operating System :: OS Independent
Requires-Python: >=3.5
